adam/__init__.py
adam/casadi/__init__.py
adam/casadi/casadi_like.py
adam/casadi/computations.py
adam/casadi/inverse_kinematics.py
adam/core/__init__.py
adam/core/array_api_math.py
adam/core/constants.py
adam/core/rbd_algorithms.py
adam/core/spatial_math.py
adam/jax/__init__.py
adam/jax/computations.py
adam/jax/jax_like.py
adam/model/__init__.py
adam/model/abc_factories.py
adam/model/factory.py
adam/model/kindyn_mixin.py
adam/model/model.py
adam/model/tree.py
adam/model/conversions/__init__.py
adam/model/conversions/idyntree.py
adam/model/mj_factory/__init__.py
adam/model/mj_factory/mujoco_model.py
adam/model/std_factories/__init__.py
adam/model/std_factories/std_joint.py
adam/model/std_factories/std_link.py
adam/model/std_factories/std_model.py
adam/numpy/__init__.py
adam/numpy/computations.py
adam/numpy/numpy_like.py
adam/parametric/__init__.py
adam/parametric/casadi/__init__.py
adam/parametric/casadi/computations_parametric.py
adam/parametric/jax/__init__.py
adam/parametric/jax/computations_parametric.py
adam/parametric/model/__init__.py
adam/parametric/model/parametric_factories/__init__.py
adam/parametric/model/parametric_factories/parametric_joint.py
adam/parametric/model/parametric_factories/parametric_link.py
adam/parametric/model/parametric_factories/parametric_model.py
adam/parametric/numpy/__init__.py
adam/parametric/numpy/computations_parametric.py
adam/parametric/pytorch/__init__.py
adam/parametric/pytorch/computations_parametric.py
adam/pytorch/__init__.py
adam/pytorch/computation_batch.py
adam/pytorch/computations.py
adam/pytorch/torch_like.py
adam_robotics-0.5.0.dist-info/licenses/LICENSE
adam_robotics-0.5.0.dist-info/METADATA
adam_robotics-0.5.0.dist-info/WHEEL
adam_robotics-0.5.0.dist-info/top_level.txt
adam_robotics-0.5.0.dist-info/RECORD
