Metadata-Version: 2.4
Name: adam-robotics
Version: 0.5.0
Summary: Automatic Differentiation for rigid-body-dynamics AlgorithMs
Author-email: Giuseppe L'Erario <gl.giuseppelerario@gmail.com>
License: BSD 3-Clause License
Project-URL: Documentation, https://adam-robotics.readthedocs.io/en/latest/
Project-URL: Source, https://github.com/ami-iit/adam
Keywords: robotics,urdf,rigid body dynamics,featherstone,automatic differentiation,optimization,casadi,jax,pytorch,reinforcement-learning,motion-planning
Requires-Python: >=3.10
License-File: LICENSE
Requires-Dist: numpy>=1.20
Requires-Dist: scipy
Requires-Dist: casadi>=3.6
Requires-Dist: prettytable
Requires-Dist: urdfdom-py
Requires-Dist: array-api-compat
Provides-Extra: jax
Requires-Dist: jax<=0.6.0; extra == "jax"
Requires-Dist: jaxlib; extra == "jax"
Provides-Extra: casadi
Requires-Dist: casadi; extra == "casadi"
Requires-Dist: liecasadi; extra == "casadi"
Provides-Extra: pytorch
Requires-Dist: torch; extra == "pytorch"
Requires-Dist: jax; extra == "pytorch"
Requires-Dist: jaxlib; extra == "pytorch"
Provides-Extra: test
Requires-Dist: jax<=0.6.0; extra == "test"
Requires-Dist: jaxlib; extra == "test"
Requires-Dist: casadi; extra == "test"
Requires-Dist: torch; extra == "test"
Requires-Dist: mujoco; extra == "test"
Requires-Dist: robot_descriptions; extra == "test"
Requires-Dist: pytest; extra == "test"
Requires-Dist: idyntree; extra == "test"
Requires-Dist: icub-models; extra == "test"
Requires-Dist: black; extra == "test"
Requires-Dist: requests; extra == "test"
Requires-Dist: liecasadi; extra == "test"
Provides-Extra: conversion
Requires-Dist: idyntree; extra == "conversion"
Provides-Extra: all
Requires-Dist: jax; extra == "all"
Requires-Dist: jaxlib; extra == "all"
Requires-Dist: casadi>=3.6; extra == "all"
Requires-Dist: torch; extra == "all"
Dynamic: license-file
